techalib-0.1.0.dist-info/METADATA
techalib-0.1.0.dist-info/WHEEL
techalib-0.1.0.dist-info/licenses/LICENSE
techalib/__init__.py
techalib/_core.abi3.so
techalib/_core/__init__.pyi
techalib/_core/ad.pyi
techalib/_core/adx.pyi
techalib/_core/aroon.pyi
techalib/_core/aroonosc.pyi
techalib/_core/atr.pyi
techalib/_core/bbands.pyi
techalib/_core/dema.pyi
techalib/_core/dx.pyi
techalib/_core/ema.pyi
techalib/_core/kama.pyi
techalib/_core/macd.pyi
techalib/_core/midpoint.pyi
techalib/_core/midprice.pyi
techalib/_core/minus_di.pyi
techalib/_core/minus_dm.pyi
techalib/_core/plus_di.pyi
techalib/_core/plus_dm.pyi
techalib/_core/roc.pyi
techalib/_core/rocr.pyi
techalib/_core/rsi.pyi
techalib/_core/sma.pyi
techalib/_core/t3.pyi
techalib/_core/tema.pyi
techalib/_core/trima.pyi
techalib/_core/wma.pyi
techalib/maptypes.py
techalib/py.typed
techalib-0.1.0.dist-info/RECORD
