Metadata-Version: 2.4
Name: techalib
Version: 0.1.0
License-File: LICENSE
Summary: Techalib: A TECHnical Analysis LIBrary
Keywords: technical analysis,finance,trading,indicators,ta
Author: Guitheg
Author-email: Guillaume GOBIN <gthgobin@gmail.com>
License: BSD-3-Clause
Project-URL: Source Code, https://github.com/Guitheg/techalib.git
